zipf/__init__.py
zipf/zipf.py
zipfs-1.0.5.dist-info/LICENSE
zipfs-1.0.5.dist-info/METADATA
zipfs-1.0.5.dist-info/WHEEL
zipfs-1.0.5.dist-info/entry_points.txt
zipfs-1.0.5.dist-info/top_level.txt
zipfs-1.0.5.dist-info/RECORD
