Metadata-Version: 2.1
Name: zipfs
Version: 1.0.5
Summary: CLI tool to directly zip several files/folders or an existing folder
Home-page: https://github.com/yoarch/zipf
Author: yoarch
Author-email: yo.managements@gmail.com
License: UNKNOWN
Platform: UNKNOWN
Classifier: Programming Language :: Python :: 3
Classifier: License :: OSI Approved :: MIT License
Classifier: Operating System :: OS Independent
Requires-Python: >=3
